koboextractor/__init__.py
koboextractor-0.2.1.dist-info/LICENSE
koboextractor-0.2.1.dist-info/METADATA
koboextractor-0.2.1.dist-info/WHEEL
koboextractor-0.2.1.dist-info/top_level.txt
koboextractor-0.2.1.dist-info/RECORD
