Metadata-Version: 2.1
Name: koboextractor
Version: 0.2.1
Summary: Extract datasets from KoBoToolbox
Home-page: https://github.com/heiko-r/koboextractor
Author: Heiko Rothkranz
License: UNKNOWN
Project-URL: Documentation, https://koboextractor.readthedocs.io
Project-URL: Source, https://github.com/heiko-r/koboextractor/
Project-URL: Tracker, https://github.com/heiko-r/koboextractor/issues
Keywords: KoBoToolbox
Platform: UNKNOWN
Classifier: Programming Language :: Python :: 3
Classifier: License :: OSI Approved :: MIT License
Classifier: Operating System :: OS Independent
Requires-Python: >=3.6
